networkinference/__init__.py
networkinference/core.py
networkinference/inference.py
networkinference/utils/__init__.py
networkinference/utils/tools.py
networkinference-0.0.4.dist-info/LICENSE.txt
networkinference-0.0.4.dist-info/METADATA
networkinference-0.0.4.dist-info/WHEEL
networkinference-0.0.4.dist-info/top_level.txt
networkinference-0.0.4.dist-info/RECORD
