Metadata-Version: 2.1
Name: networkinference
Version: 0.0.4
Summary: Inferential tools for network-dependent data.
Home-page: https://github.com/mpleung/networkinference
Author: Michael P. Leung
Author-email: no@spam.com
License: BSD 3-Clause License
Classifier: Development Status :: 3 - Alpha
Classifier: Intended Audience :: Science/Research
Classifier: License :: OSI Approved :: BSD License
Classifier: Programming Language :: Python :: 3
Classifier: Programming Language :: Python :: 3.6
Classifier: Programming Language :: Python :: 3.7
Classifier: Programming Language :: Python :: 3.8
Classifier: Programming Language :: Python :: 3.9
Classifier: Operating System :: OS Independent
Classifier: Topic :: Scientific/Engineering
Requires-Python: >=3.6
License-File: LICENSE.txt
Requires-Dist: matplotlib >=3.4
Requires-Dist: networkx >=2.6
Requires-Dist: numpy >=1.21
Requires-Dist: scikit-learn >=0.24
Requires-Dist: scipy >=1.7
Requires-Dist: seaborn >=0.11
Requires-Dist: tabulate >=0.8
